lab3/buffer_circular.sv
module BufferCircular #(
  parameter WIDTH = 64,
  parameter NUM = 8,
  localparam INDEX_SIZE = $clog2(NUM)
)(
  input logic 				clk_i, 			// Senyal de reloj
  input logic 				rstn_i, 		// Senyal negada de reset
  input logic 				insercion_i, 	// Senyal de insercion
  input logic [WIDTH-1:0] 	dato_i, 		// Dato a insertar
  input logic 				delecion_i, 	// Senyal de delecion
  output logic [WIDTH-1:0] 	dato_o, 		// Dato leido
  output logic 				vacia_o, 		// Senyal de cola vacıa
  output logic 				llena_o 		// Senyal de cola llena
);
// Instanciamos los registros WIDTHxNUM
logic [WIDTH-1:0] registers_q [NUM-1:0];
// Instanciamos punteros de control
logic [INDEX_SIZE-1:0] cola_q, cabeza_q;
// Instanciamos senyales de control
logic permiso_insercion, permiso_delecion;
logic [INDEX_SIZE:0] num_q;

// Logica de insercion
assign permiso_insercion = (num_q < NUM) & (insercion_i);
// L´ogica de delecion
assign permiso_delecion = (num_q > 0) & (delecion_i);
// Logica de Lectura. Solo lee si hay un dato
assign dato_o = (vacia_o) ? 'h0 : registers_q[cabeza_q]; //

// Logica de Escritura.
always_ff @(posedge clk_i, negedge rstn_i) begin
  if (~rstn_i) begin
    for (int i=0; i<NUM; ++i) begin
      registers_q[i] <= 'h0;
    end
  end else if (permiso_insercion) begin
    registers_q[cola_q] <= dato_i; //
  end
end

// Logica de Control
always_ff @(posedge clk_i, negedge rstn_i) begin
  if (!rstn_i) begin
    cabeza_q <= 'h0;
    cola_q <= 'h0;
    num_q <= 'h0;
  end else begin
    cabeza_q <= cabeza_q + {2'b0, permiso_delecion}; //
    cola_q <= cola_q + {2'b0, permiso_insercion}; //
    num_q <= num_q + {3'b0, permiso_insercion} - {3'b0, permiso_delecion}; //
  end
end

assign vacia_o = (num_q == 0);

assign llena_o = ((num_q == NUM) | !(rstn_i));

endmodule

lab3/tb_buffer_circular.sv
module tb_buffer_circular;

    parameter WIDTH = 32;
    parameter NUM = 8;
    parameter INDEX_SIZE = $clog2(NUM);
    // Signal declaration
    reg				  clk; 			// Senyal de reloj
    reg 				rstn; 		// Senyal negada de reset
    reg 				insercion; 	// Senyal de insercion
    reg [WIDTH-1:0] 	dato_i; 		// Dato a insertar
    reg 				delecion; 	// Senyal de delecion
    wire [WIDTH-1:0] 	dato_o; 		// Dato leido
    wire 				vacia; 		// Senyal de cola vacıa
    wire 				llena; 		// Senyal de cola llena
    integer i;

    initial begin
        
    end

    // Instance of the full_adder under test
    BufferCircular #( .WIDTH(WIDTH), .NUM(NUM)) CD (
      .clk_i(clk), 			   // Senyal de reloj
  		.rstn_i(rstn), 		       // Senyal negada de reset
      .insercion_i(insercion),
      .dato_i(dato_i),
      .delecion_i(delecion),
      .dato_o(dato_o),
      .vacia_o(vacia),
      .llena_o(llena)
    );

    // Basic test for all the input combinations
    task basic_functional_testing();
        $display(" ------------------------------------------------");
        $display(" Basic test ");
        $display(" ------------------------------------------------");

        clk = 1; rstn = 0;
        #500 clk = 0; rstn = 1;
        #500;
        for (i=1; i<=8; i++) begin
             clk = 1;
             insercion = 1;
             dato_i = i[WIDTH-1:0];
             #500 clk = 0;
             insercion = 0;
             #500; 
        end
    endtask

    /*
    * TESTS A HACER
    *
      * Que vaya escribiendo y leyendo
      * Que pasa si llega al final y lee / escribe?
      * */



    // Main execution flow of the testbench
    initial begin 
        // wavefrom generation
        $dumpfile("waveform.vcd");
        $dumpvars();

        // Functionality testing of the 
        basic_functional_testing();
        $finish();
    end
                 
endmodule

labs/lab3/waveform.vcd
$version Generated by VerilatedVcd $end
$timescale 1ps $end
 $scope module TOP $end
  $scope module tb_buffer_circular $end
   $var wire 32 9 WIDTH [31:0] $end
   $var wire 32 : NUM [31:0] $end
   $var wire 32 ; INDEX_SIZE [31:0] $end
   $var wire 1 # clk $end
   $var wire 1 $ rstn $end
   $var wire 1 % insercion $end
   $var wire 32 & dato_i [31:0] $end
   $var wire 1 < delecion $end
   $var wire 32 ( dato_o [31:0] $end
   $var wire 1 ) vacia $end
   $var wire 1 7 llena $end
   $var wire 32 ' i [31:0] $end
   $scope module CD $end
    $var wire 32 9 WIDTH [31:0] $end
    $var wire 32 : NUM [31:0] $end
    $var wire 32 ; INDEX_SIZE [31:0] $end
    $var wire 1 # clk_i $end
    $var wire 1 $ rstn_i $end
    $var wire 1 % insercion_i $end
    $var wire 32 & dato_i [31:0] $end
    $var wire 1 < delecion_i $end
    $var wire 32 ( dato_o [31:0] $end
    $var wire 1 ) vacia_o $end
    $var wire 1 7 llena_o $end
    $var wire 32 * registers_q[0] [31:0] $end
    $var wire 32 + registers_q[1] [31:0] $end
    $var wire 32 , registers_q[2] [31:0] $end
    $var wire 32 - registers_q[3] [31:0] $end
    $var wire 32 . registers_q[4] [31:0] $end
    $var wire 32 / registers_q[5] [31:0] $end
    $var wire 32 0 registers_q[6] [31:0] $end
    $var wire 32 1 registers_q[7] [31:0] $end
    $var wire 3 2 cola_q [2:0] $end
    $var wire 3 3 cabeza_q [2:0] $end
    $var wire 1 8 permiso_insercion $end
    $var wire 1 4 permiso_delecion $end
    $var wire 4 5 num_q [3:0] $end
    $scope module unnamedblk1 $end
     $var wire 32 6 i [31:0] $end
    $upscope $end
   $upscope $end
  $upscope $end
 $upscope $end
$enddefinitions $end


#0
1#
0$
0%
b00000000000000000000000000000000 &
b00000000000000000000000000000000 '
b00000000000000000000000000000000 (
1)
b00000000000000000000000000000000 *
b00000000000000000000000000000000 +
b00000000000000000000000000000000 ,
b00000000000000000000000000000000 -
b00000000000000000000000000000000 .
b00000000000000000000000000000000 /
b00000000000000000000000000000000 0
b00000000000000000000000000000000 1
b000 2
b000 3
04
b0000 5
b00000000000000000000000000000000 6
17
08
b00000000000000000000000000100000 9
b00000000000000000000000000001000 :
b00000000000000000000000000000011 ;
0<
#500
0#
1$
07
#1000
1#
1%
b00000000000000000000000000000001 &
b00000000000000000000000000000001 (
0)
b00000000000000000000000000000001 *
b001 2
b0001 5
18
#1500
0#
0%
08
#2000
1#
1%
b00000000000000000000000000000010 &
b00000000000000000000000000000010 '
b00000000000000000000000000000010 +
b010 2
b0010 5
18
#2500
0#
0%
08
#3000
1#
1%
b00000000000000000000000000000011 &
b00000000000000000000000000000011 '
b00000000000000000000000000000011 ,
b011 2
b0011 5
18
#3500
0#
0%
08
#4000
1#
1%
b00000000000000000000000000000100 &
b00000000000000000000000000000100 '
b00000000000000000000000000000100 -
b100 2
b0100 5
18
#4500
0#
0%
08
#5000
1#
1%
b00000000000000000000000000000101 &
b00000000000000000000000000000101 '
b00000000000000000000000000000101 .
b101 2
b0101 5
18
#5500
0#
0%
08
#6000
1#
1%
b00000000000000000000000000000110 &
b00000000000000000000000000000110 '
b00000000000000000000000000000110 /
b110 2
b0110 5
18
#6500
0#
0%
08
#7000
1#
1%
b00000000000000000000000000000111 &
b00000000000000000000000000000111 '
b00000000000000000000000000000111 0
b111 2
b0111 5
18
#7500
0#
0%
08
#8000
1#
1%
b00000000000000000000000000001000 &
b00000000000000000000000000001000 '
b00000000000000000000000000001000 1
b000 2
b1000 5
17
#8500
0#
0%
#9000
b00000000000000000000000000001001 '
